scholarsync/__init__.py
scholarsync/aio.py
scholarsync/data/LICENSE.txt
scholarsync/data/README.md
scholarsync/data/help.txt
scholarsync/data/requirements.txt
scholarsync-0.0.3.88.dist-info/LICENSE
scholarsync-0.0.3.88.dist-info/METADATA
scholarsync-0.0.3.88.dist-info/WHEEL
scholarsync-0.0.3.88.dist-info/entry_points.txt
scholarsync-0.0.3.88.dist-info/top_level.txt
scholarsync-0.0.3.88.dist-info/RECORD
