Metadata-Version: 2.1
Name: scholarsync
Version: 0.0.3.88
Summary: The Literature mining and processing utility
Home-page: UNKNOWN
Author: Amit
Author-email: idonthaveemail@mail.com
License: UNKNOWN
Platform: UNKNOWN
License-File: LICENSE
Requires-Dist: biopython
Requires-Dist: requests
Requires-Dist: beautifulsoup4
Requires-Dist: PyPDF2
Requires-Dist: numpy
Requires-Dist: plotly
Requires-Dist: lxml
Requires-Dist: spacy >=3.7.5
Requires-Dist: pandas
Requires-Dist: scikit-learn
